typed_trie/__init__.py
typed_trie/trie.py
typed_trie-0.1.0.dist-info/LICENSE
typed_trie-0.1.0.dist-info/METADATA
typed_trie-0.1.0.dist-info/WHEEL
typed_trie-0.1.0.dist-info/RECORD
