Metadata-Version: 2.1
Name: typed-trie
Version: 0.1.0
Summary: A pure Python implementation of a trie with typing.
Home-page: https://github.com/henadzit/typed-trie
License: MIT
Keywords: trie
Author: henadzit
Author-email: henadzi.tsaryk@gmail.com
Requires-Python: >=3.11,<4.0
Classifier: License :: OSI Approved :: MIT License
Classifier: Programming Language :: Python
Classifier: Programming Language :: Python :: 3
Classifier: Programming Language :: Python :: 3.11
Classifier: Programming Language :: Python :: 3.12
Project-URL: Repository, https://github.com/henadzit/typed-trie
